dvpOAuth/__init__.py
dvpOAuth/class_OAuth.py
dvpOAuth/error.py
dvpOAuth/util.py
pyuspsaddress/__init__.py
pyuspsaddress/constants.py
pyuspsaddress/error.py
pyuspsaddress/errors.py
pyuspsaddress/pyuspsaddress.py
pyuspsaddress-0.0.2.dist-info/LICENSE
pyuspsaddress-0.0.2.dist-info/METADATA
pyuspsaddress-0.0.2.dist-info/WHEEL
pyuspsaddress-0.0.2.dist-info/top_level.txt
pyuspsaddress-0.0.2.dist-info/RECORD
